connector/__init__.py
connector/sql_helper_connector.py
connector/util.py
connector/worker_agent.py
sql_helper_connector-0.1.4.dist-info/LICENSE
sql_helper_connector-0.1.4.dist-info/METADATA
sql_helper_connector-0.1.4.dist-info/WHEEL
sql_helper_connector-0.1.4.dist-info/entry_points.txt
sql_helper_connector-0.1.4.dist-info/top_level.txt
sql_helper_connector-0.1.4.dist-info/RECORD
